lost_years/__init__.py
lost_years/data/consolidate_data.py
lost_years/data/hld/formats.pdf
lost_years/data/hld/hld.csv.gz
lost_years/data/schemas.py
lost_years/data/ssa/ssa.csv
lost_years/data/who/who-lt-backup-20251122.csv.gz
lost_years/data/who/who-lt.csv.gz
lost_years/data/who/who.csv.gz
lost_years/data_sources.json
lost_years/hld.py
lost_years/ssa.py
lost_years/types.py
lost_years/utils.py
lost_years/who.py
lost_years-0.7.0.dist-info/WHEEL
lost_years-0.7.0.dist-info/entry_points.txt
lost_years-0.7.0.dist-info/METADATA
lost_years-0.7.0.dist-info/RECORD
