Metadata-Version: 2.4
Name: lost_years
Version: 0.7.0
Summary: Get Expected Number of Years Lost
Keywords: lost years,life expectancy,human life table,mortality,actuarial
Author: Suriyan Laohaprapanon, Gaurav Sood
Author-email: Suriyan Laohaprapanon <suriyant@gmail.com>, Gaurav Sood <gsood07@gmail.com>
License-Expression: MIT
Classifier: Development Status :: 4 - Beta
Classifier: Intended Audience :: Developers
Classifier: Intended Audience :: Science/Research
Classifier: Programming Language :: Python :: 3
Classifier: Programming Language :: Python :: 3.12
Classifier: Programming Language :: Python :: 3.13
Classifier: Programming Language :: Python :: 3.14
Classifier: Topic :: Scientific/Engineering :: Information Analysis
Classifier: Topic :: Software Development :: Libraries :: Python Modules
Classifier: Topic :: Utilities
Requires-Dist: beautifulsoup4>=4.14.2
Requires-Dist: pandas
Requires-Dist: requests
Requires-Dist: selenium>=4.38.0
Requires-Dist: lost-years[test] ; extra == 'dev'
Requires-Dist: ruff>=0.14.6 ; extra == 'dev'
Requires-Dist: pandas-stubs ; extra == 'dev'
Requires-Dist: pydoclint>=0.5.0 ; extra == 'dev'
Requires-Dist: pyright[nodejs]>=1.1.0 ; extra == 'dev'
Requires-Dist: sphinx>=7.0 ; extra == 'docs'
Requires-Dist: furo ; extra == 'docs'
Requires-Dist: sphinx-autodoc-typehints ; extra == 'docs'
Requires-Dist: myst-parser ; extra == 'docs'
Requires-Dist: nbsphinx>=0.9.0 ; extra == 'docs'
Requires-Dist: ipykernel>=6.0 ; extra == 'docs'
Requires-Dist: matplotlib>=3.7 ; extra == 'docs'
Requires-Dist: seaborn>=0.12 ; extra == 'docs'
Requires-Dist: pytest>=7.0 ; extra == 'test'
Requires-Dist: pytest-cov ; extra == 'test'
Requires-Dist: coverage ; extra == 'test'
Maintainer: Suriyan Laohaprapanon, Gaurav Sood
Maintainer-email: Suriyan Laohaprapanon <suriyant@gmail.com>, Gaurav Sood <gsood07@gmail.com>
Requires-Python: >=3.12
Project-URL: Documentation, https://gojiplus.github.io/lost-years/
Project-URL: Homepage, https://github.com/gojiplus/lost_years
Project-URL: Issues, https://github.com/gojiplus/lost_years/issues
Project-URL: Repository, https://github.com/gojiplus/lost_years.git
Provides-Extra: dev
Provides-Extra: docs
Provides-Extra: test
